MANIFEST.in
setup.cfg
setup.py
bitcoinaverage/__init__.py
bitcoinaverage/_config.py
bitcoinaverage/exceptions.py
bitcoinaverage.egg-info/PKG-INFO
bitcoinaverage.egg-info/SOURCES.txt
bitcoinaverage.egg-info/dependency_links.txt
bitcoinaverage.egg-info/requires.txt
bitcoinaverage.egg-info/top_level.txt
bitcoinaverage/clients/__init__.py
bitcoinaverage/clients/_base_client.py
bitcoinaverage/clients/restful_client.py
bitcoinaverage/clients/websocket_client.py
bitcoinaverage/clients/__pycache__/__init__.cpython-34.pyc
bitcoinaverage/clients/__pycache__/_base_client.cpython-34.pyc
bitcoinaverage/clients/__pycache__/restful_client.cpython-34.pyc
bitcoinaverage/clients/__pycache__/websocket_client.cpython-34.pyc
bitcoinaverage/examples/__init__.py
bitcoinaverage/examples/constants.py
bitcoinaverage/examples/conversions.py
bitcoinaverage/examples/exchange_websocket.py
bitcoinaverage/examples/exchanges.py
bitcoinaverage/examples/history.py
bitcoinaverage/examples/ticker.py
bitcoinaverage/examples/ticker_websocket.py
bitcoinaverage/examples/websocket_examples.py