Metadata-Version: 1.0
Name: bitcoinaverage
Version: 0.1.13
Summary: Library to integrate with the BitcoinAverage API
Home-page: UNKNOWN
Author: Blockchain Data LTD
Author-email: info@bitcoinaverage.com
License: UNKNOWN
Keywords: bitcoinaverage,bitcoin,api
Platform: UNKNOWN
